[
  {
    "pk": 6, 
    "model": "progdb2.person", 
    "fields": {
      "memnum": -1, 
      "complete": "No", 
      "firstName": "Deria", 
      "tags": [], 
      "middleName": "", 
      "lastName": "Book", 
      "pubNotes": "", 
      "contact": "", 
      "privNotes": "", 
      "badge": "Shepherd Book", 
      "email": ""
    }
  }, 
  {
    "pk": 3, 
    "model": "progdb2.person", 
    "fields": {
      "memnum": -1, 
      "complete": "No", 
      "firstName": "Jayne", 
      "tags": [], 
      "middleName": "", 
      "lastName": "Cobb", 
      "pubNotes": "", 
      "contact": "", 
      "privNotes": "", 
      "badge": "", 
      "email": ""
    }
  }, 
  {
    "pk": 10, 
    "model": "progdb2.person", 
    "fields": {
      "memnum": -1, 
      "complete": "No", 
      "firstName": "Rubert", 
      "tags": [], 
      "middleName": "", 
      "lastName": "Giles", 
      "pubNotes": "", 
      "contact": "", 
      "privNotes": "", 
      "badge": "Ripper", 
      "email": ""
    }
  }, 
  {
    "pk": 7, 
    "model": "progdb2.person", 
    "fields": {
      "memnum": -1, 
      "complete": "No", 
      "firstName": "Alexander", 
      "tags": [], 
      "middleName": "", 
      "lastName": "Harris", 
      "pubNotes": "", 
      "contact": "", 
      "privNotes": "", 
      "badge": "Xander", 
      "email": ""
    }
  }, 
  {
    "pk": 2, 
    "model": "progdb2.person", 
    "fields": {
      "memnum": -1, 
      "complete": "No", 
      "firstName": "Malcolm", 
      "tags": [], 
      "middleName": "", 
      "lastName": "Reynolds", 
      "pubNotes": "", 
      "contact": "", 
      "privNotes": "", 
      "badge": "Mal", 
      "email": ""
    }
  }, 
  {
    "pk": 9, 
    "model": "progdb2.person", 
    "fields": {
      "memnum": -1, 
      "complete": "No", 
      "firstName": "Willow", 
      "tags": [], 
      "middleName": "", 
      "lastName": "Rosenburg", 
      "pubNotes": "", 
      "contact": "", 
      "privNotes": "", 
      "badge": "", 
      "email": ""
    }
  }, 
  {
    "pk": 8, 
    "model": "progdb2.person", 
    "fields": {
      "memnum": -1, 
      "complete": "No", 
      "firstName": "Buffy", 
      "tags": [], 
      "middleName": "", 
      "lastName": "Summers", 
      "pubNotes": "", 
      "contact": "", 
      "privNotes": "", 
      "badge": "She who hangs out in graveyards", 
      "email": ""
    }
  }, 
  {
    "pk": 11, 
    "model": "progdb2.person", 
    "fields": {
      "memnum": -1, 
      "complete": "No", 
      "firstName": "Dawn", 
      "tags": [], 
      "middleName": "", 
      "lastName": "Summers", 
      "pubNotes": "", 
      "contact": "", 
      "privNotes": "", 
      "badge": "Dawnie", 
      "email": ""
    }
  }, 
  {
    "pk": 5, 
    "model": "progdb2.person", 
    "fields": {
      "memnum": -1, 
      "complete": "No", 
      "firstName": "River", 
      "tags": [], 
      "middleName": "", 
      "lastName": "Tam", 
      "pubNotes": "", 
      "contact": "", 
      "privNotes": "", 
      "badge": "", 
      "email": ""
    }
  }, 
  {
    "pk": 4, 
    "model": "progdb2.person", 
    "fields": {
      "memnum": -1, 
      "complete": "No", 
      "firstName": "Simon", 
      "tags": [], 
      "middleName": "", 
      "lastName": "Tam", 
      "pubNotes": "", 
      "contact": "", 
      "privNotes": "", 
      "badge": "", 
      "email": ""
    }
  }
]